MANIFEST.in
README.md
setup.py
theano_lstm/__init__.py
theano_lstm/masked_loss.py
theano_lstm/shared_memory.py
theano_lstm.egg-info/PKG-INFO
theano_lstm.egg-info/SOURCES.txt
theano_lstm.egg-info/dependency_links.txt
theano_lstm.egg-info/not-zip-safe
theano_lstm.egg-info/requires.txt
theano_lstm.egg-info/top_level.txt