Metadata-Version: 1.1
Name: theano-lstm
Version: 0.0.14
Summary: Nano size theano lstm module
Home-page: https://github.com/JonathanRaiman/theano_lstm
Author: Jonathan Raiman
Author-email: jraiman at mit dot edu
License: MIT
Download-URL: https://github.com/JonathanRaiman/theano_lstm
Keywords: Gradient Descent,Theano,LSTM,neural networks
Platform: any
Classifier: Intended Audience :: Science/Research
Classifier: Operating System :: OS Independent
Classifier: Programming Language :: Python :: 3.3
Classifier: Programming Language :: Python :: 2.7
Classifier: Topic :: Scientific/Engineering :: Artificial Intelligence
Classifier: Topic :: Scientific/Engineering :: Mathematics
